ttclust/__init__.py
ttclust/ttclust.py
ttclust/version.py
ttclust-4.10.4.dist-info/LICENSE
ttclust-4.10.4.dist-info/METADATA
ttclust-4.10.4.dist-info/WHEEL
ttclust-4.10.4.dist-info/entry_points.txt
ttclust-4.10.4.dist-info/top_level.txt
ttclust-4.10.4.dist-info/RECORD
